portid_sdk/__init__.py
portid_sdk/api.py
portid_sdk/encryption.py
portid_sdk/exceptions.py
harboria_portid-0.1.0.dist-info/METADATA
harboria_portid-0.1.0.dist-info/WHEEL
harboria_portid-0.1.0.dist-info/top_level.txt
harboria_portid-0.1.0.dist-info/RECORD
