Metadata-Version: 2.4
Name: harboria-portid
Version: 0.1.0
Summary: A client-side SDK for a zero-knowledge, decentralized user data sync system.
Home-page: https://github.com/Harboria-Labs/PortID
Author: Harboria Labs
Author-email: contact@harboria.com
Classifier: Development Status :: 4 - Beta
Classifier: Intended Audience :: Developers
Classifier: Programming Language :: Python :: 3
Classifier: License :: OSI Approved :: MIT License
Classifier: Operating System :: OS Independent
Classifier: Topic :: Security :: Cryptography
Classifier: Topic :: Software Development :: Libraries :: Python Modules
Requires-Python: >=3.6
Requires-Dist: requests
Requires-Dist: pycryptodome
Dynamic: author
Dynamic: author-email
Dynamic: classifier
Dynamic: description
Dynamic: description-content-type
Dynamic: home-page
Dynamic: requires-dist
Dynamic: requires-python
Dynamic: summary
